LAMBDA/__init__.py
LAMBDA/computeADOP.py
lambda_python-0.1.0.dist-info/licenses/LICENSE
lambda_python-0.1.0.dist-info/licenses/NOTICE
lambda_python-0.1.0.dist-info/METADATA
lambda_python-0.1.0.dist-info/WHEEL
lambda_python-0.1.0.dist-info/top_level.txt
lambda_python-0.1.0.dist-info/RECORD
