Metadata-Version: 2.4
Name: LAMBDA-Python
Version: 0.1.0
Summary: Least-squares AMBiguity Decorrelation Adjustment (LAMBDA) method
Author: Sandra Verhagen
Author-email: Lotfi Massarweh <lotfimassarweh@gmail.com>
Project-URL: repository, https://github.com/LotfiMassarweh/LAMBDA-Python.git
Keywords: gnss,integer ambiguity resolution,mixed-integer models
Classifier: Development Status :: 5 - Production/Stable
Classifier: Intended Audience :: Science/Research
Classifier: Natural Language :: English
Classifier: Programming Language :: Python :: 3.10
Classifier: Programming Language :: Python :: 3.11
Classifier: Programming Language :: Python :: 3.12
Requires-Python: >=3.10
License-File: LICENSE
License-File: NOTICE
Requires-Dist: scipy
Requires-Dist: numpy
Provides-Extra: dev
Requires-Dist: pytest; extra == "dev"
Requires-Dist: pytest-cov; extra == "dev"
Requires-Dist: pycodestyle; extra == "dev"
Requires-Dist: ruff; extra == "dev"
Requires-Dist: pre-commit; extra == "dev"
Provides-Extra: docs
Requires-Dist: mkdocs; extra == "docs"
Requires-Dist: mkdocs-material; extra == "docs"
Requires-Dist: mkdocs-jupyter; extra == "docs"
Requires-Dist: mkdocstrings[python]; extra == "docs"
Requires-Dist: mkdocs-gen-files; extra == "docs"
Provides-Extra: demo
Requires-Dist: jupyterlab; extra == "demo"
Requires-Dist: matplotlib; extra == "demo"
Dynamic: license-file
